__init__.py
pepNmemb/__init__.py
pepNmemb/py.typed
pepNmemb/scripts/__init__.py
pepNmemb/scripts/classes.py
pepNmemb/scripts/get_hbonds_pep_lipid.py
pepNmemb/scripts/get_insertion.py
pepNmemb/scripts/get_interactions_inter_pep.py
pepNmemb/scripts/get_lipid_apl.py
pepNmemb/scripts/get_tilt_angle.py
pepNmemb/scripts/utils.py
pepnmemb-0.0.2.dist-info/licenses/LICENSE
pepnmemb-0.0.2.dist-info/METADATA
pepnmemb-0.0.2.dist-info/WHEEL
pepnmemb-0.0.2.dist-info/top_level.txt
pepnmemb-0.0.2.dist-info/RECORD
